phy/__init__.py
phy/conftest.py
phy/cluster/__init__.py
phy/cluster/manual/__init__.py
phy/cluster/manual/_history.py
phy/cluster/manual/_utils.py
phy/cluster/manual/clustering.py
phy/cluster/manual/controller.py
phy/cluster/manual/gui_component.py
phy/cluster/manual/views.py
phy/cluster/manual/tests/__init__.py
phy/cluster/manual/tests/conftest.py
phy/cluster/manual/tests/test_clustering.py
phy/cluster/manual/tests/test_controller.py
phy/cluster/manual/tests/test_gui_component.py
phy/cluster/manual/tests/test_history.py
phy/cluster/manual/tests/test_utils.py
phy/cluster/manual/tests/test_views.py
phy/cluster/tests/__init__.py
phy/electrode/__init__.py
phy/electrode/mea.py
phy/electrode/probes/1x32_buzsaki.prb
phy/electrode/tests/__init__.py
phy/electrode/tests/test_mea.py
phy/gui/__init__.py
phy/gui/actions.py
phy/gui/gui.py
phy/gui/qt.py
phy/gui/widgets.py
phy/gui/static/table.css
phy/gui/static/table.js
phy/gui/static/tablesort.min.js
phy/gui/static/tablesort.number.js
phy/gui/tests/__init__.py
phy/gui/tests/conftest.py
phy/gui/tests/test_actions.py
phy/gui/tests/test_gui.py
phy/gui/tests/test_qt.py
phy/gui/tests/test_widgets.py
phy/io/__init__.py
phy/io/array.py
phy/io/context.py
phy/io/datasets.py
phy/io/mock.py
phy/io/tests/__init__.py
phy/io/tests/test_array.py
phy/io/tests/test_context.py
phy/io/tests/test_datasets.py
phy/io/tests/test_mock.py
phy/plot/__init__.py
phy/plot/base.py
phy/plot/interact.py
phy/plot/panzoom.py
phy/plot/plot.py
phy/plot/transform.py
phy/plot/utils.py
phy/plot/visuals.py
phy/plot/glsl/histogram.frag
phy/plot/glsl/histogram.vert
phy/plot/glsl/line.frag
phy/plot/glsl/line.vert
phy/plot/glsl/plot.frag
phy/plot/glsl/plot.vert
phy/plot/glsl/polygon.frag
phy/plot/glsl/polygon.vert
phy/plot/glsl/scatter.frag
phy/plot/glsl/scatter.vert
phy/plot/glsl/simple.frag
phy/plot/glsl/simple.vert
phy/plot/glsl/text.frag
phy/plot/glsl/text.vert
phy/plot/glsl/uni_plot.frag
phy-1.0.9.dist-info/DESCRIPTION.rst
phy-1.0.9.dist-info/METADATA
phy-1.0.9.dist-info/RECORD
phy-1.0.9.dist-info/WHEEL
phy-1.0.9.dist-info/entry_points.txt
phy-1.0.9.dist-info/metadata.json
phy-1.0.9.dist-info/top_level.txt
